bepp/__init__.py
bepp/bepp.py
bepp-0.0.4.dist-info/METADATA
bepp-0.0.4.dist-info/WHEEL
bepp-0.0.4.dist-info/entry_points.txt
bepp-0.0.4.dist-info/licenses/LICENSE
bepp-0.0.4.dist-info/RECORD
