Metadata-Version: 2.3
Name: bepp
Version: 0.0.4
Summary: An opinionated script to gather, clean up and merge transactions from Banca Etica and PayPal.
Project-URL: Repository, https://codeberg.org/tommi/bepp
Project-URL: Issues, https://codeberg.org/tommi/bepp/issues
Project-URL: Changelog, https://codeberg.org/tommi/bepp/commits/branch/main
Author-email: Tommi <surfing@tommi.space>
License:                     GNU AFFERO GENERAL PUBLIC LICENSE
Keywords: Accounting,Banca Etica,Bank,Bank transfers,PayPal,Personal Finance Management
Classifier: Development Status :: 4 - Beta
Classifier: Environment :: Console
Classifier: License :: OSI Approved :: GNU Affero General Public License v3 or later (AGPLv3+)
Classifier: Natural Language :: English
Classifier: Natural Language :: Italian
Classifier: Operating System :: OS Independent
Classifier: Programming Language :: Python :: 3
Classifier: Programming Language :: Python :: 3.13
Classifier: Topic :: Database
Classifier: Topic :: Office/Business :: Financial :: Accounting
Classifier: Topic :: Office/Business :: Financial :: Spreadsheet
Classifier: Topic :: Scientific/Engineering :: Information Analysis
Classifier: Topic :: Utilities
Requires-Python: >=3.13
Requires-Dist: currencyconverter>=0.17.34
Requires-Dist: darkdetect>=0.8.0
Requires-Dist: pandas>=2.2.3
Requires-Dist: plotly>=5.24.1
Requires-Dist: rich-argparse>=1.6.0
Requires-Dist: rich>=13.9.4
Requires-Dist: xlrd>=2.0.1
